README.rst
setup.py
bin/sixoclock
sixoclock/__init__.py
sixoclock/backend.py
sixoclock/cache.py
sixoclock/cli.py
sixoclock/collection.py
sixoclock/config.py
sixoclock/file.py
sixoclock.egg-info/PKG-INFO
sixoclock.egg-info/SOURCES.txt
sixoclock.egg-info/dependency_links.txt
sixoclock.egg-info/requires.txt
sixoclock.egg-info/top_level.txt