Metadata-Version: 1.0
Name: sixoclock
Version: 0.1.0
Summary: Simple personal backup tool
Home-page: https://github.com/kahowell/sixoclock
Author: Kevin Howell
Author-email: kevin@kahowell.net
License: GPLv3
Platform: UNKNOWN
